setup.py
aait.egg-info/PKG-INFO
aait.egg-info/SOURCES.txt
aait.egg-info/dependency_links.txt
aait.egg-info/entry_points.txt
aait.egg-info/namespace_packages.txt
aait.egg-info/requires.txt
aait.egg-info/top_level.txt
orangecontrib/__init__.py
orangecontrib/AAIT/__init__.py
orangecontrib/AAIT/llm/__init__.py
orangecontrib/AAIT/llm/answers.py
orangecontrib/AAIT/llm/answers_llama.py
orangecontrib/AAIT/llm/chunking.py
orangecontrib/AAIT/llm/embeddings.py
orangecontrib/AAIT/llm/lemmes.py
orangecontrib/AAIT/llm/lmstudio.py
orangecontrib/AAIT/llm/process_documents.py
orangecontrib/AAIT/llm/prompt_management.py
orangecontrib/AAIT/llm/translations.py
orangecontrib/AAIT/llm/resources/__ini__.py
orangecontrib/AAIT/llm/resources/markdown_recipe.json
orangecontrib/AAIT/optimiser/__init__.py
orangecontrib/AAIT/optimiser/optuna_multi.py
orangecontrib/AAIT/utils/MetManagement.py
orangecontrib/AAIT/utils/OperationSystem.py
orangecontrib/AAIT/utils/SimpleDialogQt.py
orangecontrib/AAIT/utils/__init__.py
orangecontrib/AAIT/utils/aait_repo_file.py
orangecontrib/AAIT/utils/aait_table_viewer.py
orangecontrib/AAIT/utils/base_widget.py
orangecontrib/AAIT/utils/delta_local_shared_fodler.py
orangecontrib/AAIT/utils/import_uic.py
orangecontrib/AAIT/utils/initialize_from_ini.py
orangecontrib/AAIT/utils/mac_utils.py
orangecontrib/AAIT/utils/shared_functions.py
orangecontrib/AAIT/utils/shared_variables.py
orangecontrib/AAIT/utils/subprocess_management.py
orangecontrib/AAIT/utils/thread_management.py
orangecontrib/AAIT/utils/unlink_table_domain.py
orangecontrib/AAIT/utils/widget_positioning.py
orangecontrib/AAIT/utils/windows_utils.py
orangecontrib/AAIT/utils/tools/TigerODM_notepad.py
orangecontrib/AAIT/utils/tools/__init__.py
orangecontrib/AAIT/utils/tools/change_owcorpus.py
orangecontrib/AAIT/utils/tools/concat_splitted_pypi.py
orangecontrib/AAIT/utils/tools/first_time_check.py
orangecontrib/AAIT/utils/tools/owcorpus_ok.txt
orangecontrib/AAIT/widgets/OWAAITResourcesManager.py
orangecontrib/AAIT/widgets/OWAccumulator.py
orangecontrib/AAIT/widgets/OWAddColumns.py
orangecontrib/AAIT/widgets/OWApplyRules.py
orangecontrib/AAIT/widgets/OWAutoShowCreateInstance.py
