Metadata-Version: 2.1
Name: aait
Version: 2.3.15.996
Summary: Advanced Artificial Intelligence Tools is a package meant to develop and enable advanced AI functionalities in Orange
Home-page: 
Author: Orange community
Author-email: 
Keywords: orange3 add-on
